{
  "title": "38-sai",
  "description": "38-sai",
  "artist": "Kuroki Hidehiko",
  "author": "Kuroki Hidehiko",
  "cover": "https://i.imgur.com/8hgeGuz.png",
  "chapters": {
    "1": {
      "title": "Retaliation",
      "volume": "",
      "last_updated": "1678781239",
      "groups": {
        "": "/proxy/api/imgur/chapter/ymwrhhL"
      }
    },
    "2": {
      "title": "Aunt and Nephew",
      "volume": "",
      "last_updated": "1678782827",
      "groups": {
        "": "/proxy/api/imgur/chapter/pNdFinS"
      }
    },
    "3": {
      "title": "Would you like to peek? Part 1",
      "volume": "",
      "last_updated": "1678785092",
      "groups": {
        "": "/proxy/api/imgur/chapter/jpAKQcf"
      }
    },
    "4": {
      "title": "Would you like to peek? Part 2",
      "volume": "",
      "last_updated": "1678785781",
      "groups": {
        "": "/proxy/api/imgur/chapter/hOonXRt"
      }
    },
    "5": {
      "title": "Would you like to peek? Part 3",
      "volume": "",
      "last_updated": "1678786578",
      "groups": {
        "": "/proxy/api/imgur/chapter/ACyXiYl"
      }
    },
    "6": {
      "title": "Hot with wife",
      "volume": "",
      "last_updated": "1679200950",
      "groups": {
        "": "/proxy/api/imgur/chapter/tvhjPOn"
      }
    }
  }
}